{
  "interference": [
    {
      "question": "Какую сумму Герман перечислил физическому лицу женского пола среди всех своих исходящих переводов?",
      "answer": "5000 руб.",
      "answer_format": "Денежная сумма",
      "reasoning_path": [
        "Зимин Герман Якубович --[transferred_to]--> Емельянова Антонина Леоновна | amount: 5000 руб. | date: 28.01.2024 | method: СБП (целевое ребро)",
        "Зимин Герман Якубович --[transferred_to]--> Гущин Селиван Дорофеевич | amount: 5200 руб. | date: 08.02.2024 | method: СБП | purpose: возврат долга (похожее — другой получатель, другая сумма, другая дата)",
        "Зимин Герман Якубович --[transferred_to]--> Иванов А.С. | amount: 14800 руб. | date: 05.03.2024 | purpose: оплата услуг по дизайн-проекту ремонта (похожее — другой получатель, другая сумма, другая дата)",
        "Зимин Герман Якубович --[transferred_to]--> Получение налогового вычета | amount: 4500 руб. | date: 28.01.2024 | method: СБП (похожее — другой получатель, другая сумма)"
      ],
      "capability": "interference",
      "difficulty": "medium",
      "source_node_ids": [
        "Зимин Герман Якубович",
        "Емельянова Антонина Леоновна",
        "Гущин Селиван Дорофеевич",
        "Иванов А.С.",
        "Получение налогового вычета"
      ],
      "decoy_answers": [
        "5200 руб.",
        "4500 руб.",
        "14800 руб."
      ]
    }
  ]
}