{
    "main_spec": {
        "name": "Болеслав Эдгардович Бобров",
        "gender": "male",
        "age": 32,
        "location": "Хабаровск",
        "job_title": "Продюсер",
        "monthly_income": "185000 рублей",
        "financial_archetype": "Cash_Traditionalist: Этот человек — 'Традиционалист'. Предпочитает наличные, с трудом доверяет цифровым сервисам. Часто посещает отделения, любит бумажные договоры с печатями. Может задавать наивные вопросы о том, как работает мобильный банк или переводы.\n\n",
        "bio": "Болеслав Эдгардович, 32 года, продюсер из Хабаровска, ведёт деньги осторожно и «осязаемо». При среднем доходе 185 000 руб. в месяц он предпочитает получать и хранить часть средств наличными, доверяет бумажным документам и печатям больше, чем электронным квитанциям. Склонен к планированию бюджета: экономит на личном быту, но охотно тратит деньги на проекты и профессиональные нужды, где ценит прозрачность расчётов и договорные гарантии. Новые цифровые инструменты вызывает настороженность — мобильный банк использует минимально и часто снимает деньги «в руки» для контроля. Взаимодействует с банком лично или по телефону, требует печатных подтверждений и подробных объяснений; общается вежливо, но настойчиво, задаёт много уточняющих вопросов и просит руководителя при сомнениях.",
        "personality_traits": "Болеслав Эдгардович, 32 года, продюсер из Хабаровска, ведёт деньги осторожно и «осязаемо». При среднем доходе 185 000 руб. в месяц он предпочитает получать и хранить часть средств наличными, доверяет бумажным документам и печатям больше, чем электронным квитанциям. Склонен к планированию бюджета: экономит на личном быту, но охотно тратит деньги на проекты и профессиональные нужды, где ценит прозрачность расчётов и договорные гарантии. Новые цифровые инструменты вызывает настороженность — мобильный банк использует минимально и часто снимает деньги «в руки» для контроля. Взаимодействует с банком лично или по телефону, требует печатных подтверждений и подробных объяснений; общается вежливо, но настойчиво, задаёт много уточняющих вопросов и просит руководителя при сомнениях.",
        "id": 0
    },
    "relationships": {
        "parent": [
            {
                "id": 13,
                "gender": "female",
                "name": "Синклитикия Леоновна Федосеева",
                "age": 63
            }
        ],
        "children": [
            {
                "id": 13,
                "gender": "male",
                "name": "Парфен",
                "age": 10
            },
            {
                "id": 14,
                "gender": "male",
                "name": "Ерофей",
                "age": 10
            },
            {
                "id": 15,
                "gender": "female",
                "name": "Марина",
                "age": 12
            }
        ],
        "friends": [
            {
                "id": 10,
                "gender": "male",
                "name": "Исаев Кондратий Эдуардович",
                "age": 37
            }
        ],
        "acquaintances": [
            {
                "id": 2,
                "gender": "female",
                "name": "Фёкла Николаевна Афанасьева",
                "age": 52
            },
            {
                "id": 6,
                "gender": "male",
                "name": "Святополк Витальевич Анисимов",
                "age": 63
            }
        ]
    }
}