{
  "knowledge_update": [
    {
      "question": "На сколько процентных пунктов изменилась доходность депозита клиентки-корректора из Красновишерска между первоначальным и итоговым состоянием?",
      "answer": "2.5%",
      "answer_format": "X.X%",
      "reasoning_path": [
        "bank_product_semeyny_kapital --[had_rate]--> rate_semeyny_kapital_15_0 | value: 15.0% | date: 01.03.2024 (начальная ставка)",
        "bank_product_semeyny_kapital --[current_rate]--> rate_semeyny_kapital_12_5 | value: 12.5% | date: 10.04.2024 (итоговая ставка)",
        "вычисление: 15.0% − 12.5% = 2.5%"
      ],
      "capability": "knowledge_update",
      "difficulty": "hard",
      "source_node_ids": [
        "bank_product_semeyny_kapital",
        "rate_semeyny_kapital_15_0",
        "rate_semeyny_kapital_12_5"
      ],
      "decoy_answers": [
        "2.3%",
        "2.7%",
        "3.0%"
      ]
    }
  ]
}
